Tool
lbplistlib
