Metadata-Version: 1.0
Name: lbplistlib
Version: 1.1.0
Summary: this BIF is use for print list.
Home-page: https://www.hongkongcity.com
Author: libin
Author-email: unifacecode@163.com
License: MIT
Platform: UNKNOWN
